{"country":"BE","display_name":"Josiasmbogle","email":"josiasmbogle237@gmail.com","explicit_content":{"filter_enabled":false,"filter_locked":false},"external_urls":{"spotify":"https://open.spotify.com/user/31cym4nvgkczxngr3y3wnyi7zaxm"},"followers":{"href":null,"total":0},"href":"https://api.spotify.com/v1/users/31cym4nvgkczxngr3y3wnyi7zaxm","id":"31cym4nvgkczxngr3y3wnyi7zaxm","images":[{"height":300,"url":"https://i.scdn.co/image/ab6775700000ee857f9568c5a6a7b99c4fe3c14e","width":300},{"height":64,"url":"https://i.scdn.co/image/ab67757000003b827f9568c5a6a7b99c4fe3c14e","width":64}],"product":"free","type":"user","uri":"spotify:user:31cym4nvgkczxngr3y3wnyi7zaxm"}